ChattingBox/GPTChatter.py
ChattingBox/ModelChatter.py
ChattingBox/__init__.py
ChattingBox/GPT/Profiles.py
ChattingBox/GPT/__init__.py
chattingbox-0.0.3.dist-info/METADATA
chattingbox-0.0.3.dist-info/WHEEL
chattingbox-0.0.3.dist-info/licenses/LICENSE
chattingbox-0.0.3.dist-info/RECORD
